[
    {
        "id": 1,
        "name": "Москва",
        "coord": {
            "lon": 37.610,
            "lat": 55.755
        }
    },
    {
        "id": 2,
        "name": "Санкт Петербург",
        "coord": {
            "lon": 30.255,
            "lat": 59.900
        }
    },
    {
        "id": 3,
        "name": "Новосибирск",
        "coord": {
            "lon": 82.935,
            "lat": 55.050
        }
    },
    {
        "id": 4,
        "name": "Екатеринбург",
        "coord": {
            "lon": 60.612,
            "lat": 56.857
        }
    },
    {
        "id": 5,
        "name": "Нижний Новгород",
        "coord": {
            "lon": 44.002,
            "lat": 56.328
        }
    },
    {
        "id": 6,
        "name": "Казань",
        "coord": {
            "lon": 49.122,
            "lat": 55.788
        }
    },
    {
        "id": 7,
        "name": "Челябинск",
        "coord": {
            "lon": 61.429,
            "lat": 55.154
        }
    },
    {
        "id": 8,
        "name": "Омск",
        "coord": {
            "lon": 73.400,
            "lat": 55.000
        }
    },
    {
        "id": 9,
        "name": "Самара",
        "coord": {
            "lon": 50.150,
            "lat": 53.200
        }
    },
    {
        "id": 10,
        "name": "Уфа",
        "coord": {
            "lon": 56.037,
            "lat": 54.775
        }
    },
    {
        "id": 11,
        "name": "Красноярск",
        "coord": {
            "lon": 92.791,
            "lat": 56.009
        }
    },
    {
        "id": 12,
        "name": "Пермь",
        "coord": {
            "lon": 56.285,
            "lat": 58.017
        }
    },
    {
        "id": 13,
        "name": "Воронеж",
        "coord": {
            "lon": 39.169,
            "lat": 51.666
        }
    },
    {
        "id": 14,
        "name": "Волгоград",
        "coord": {
            "lon": 44.502,
            "lat": 48.719
        }
    },
    {
        "id": 15,
        "name": "Ульяновск",
        "coord": {
            "lon": 48.400,
            "lat": 54.333
        }
    }
]